colorthon/__init__.py
colorthon/utils.py
Colorthon-2.9.6.dist-info/METADATA
Colorthon-2.9.6.dist-info/WHEEL
Colorthon-2.9.6.dist-info/top_level.txt
Colorthon-2.9.6.dist-info/RECORD
