Metadata-Version: 2.1
Name: Colorthon
Version: 2.9.6
Summary: Colorthon Best and Fast Package For Generating Color For Text Color and Back Color Text Format
Home-page: https://github.com/colorthon/colorthon
Author: Mohammadreza Fekri
Author-email: Pymmdrza@gmail.com
License: UNKNOWN
Project-URL: Documentation, https://colorthon.gitbook.io/colorthon/
Project-URL: Personal Website, https://mmdrza.com
Keywords: color,colorthon,color package,text color,python color,color text,print color,back color,format color,colorthon package
Platform: UNKNOWN
Classifier: Programming Language :: Python :: 3
Classifier: License :: OSI Approved :: MIT License
Classifier: Operating System :: OS Independent
Requires-Python: >=3.6
